Compiled from "CollectionTest.java"
public class com.li.demo.service.impl.CollectionTest {
  public com.li.demo.service.impl.CollectionTest();
    Code:
       0: aload_0
       1: invokespecial #1                  // Method java/lang/Object."<init>":()V
       4: return

  public static void main(java.lang.String[]);
    Code:
       0: new           #2                  // class java/util/ArrayList
       3: dup
       4: invokespecial #3                  // Method java/util/ArrayList."<init>":()V
       7: astore_1
       8: aload_1
       9: iconst_1
      10: invokestatic  #4                  // Method java/lang/Integer.valueOf:(I)Ljava/lang/Integer;
      13: invokevirtual #5                  // Method java/util/ArrayList.add:(Ljava/lang/Object;)Z
      16: pop
      17: aload_1
      18: iconst_2
      19: invokestatic  #4                  // Method java/lang/Integer.valueOf:(I)Ljava/lang/Integer;
      22: invokevirtual #5                  // Method java/util/ArrayList.add:(Ljava/lang/Object;)Z
      25: pop
      26: aload_1
      27: iconst_3
      28: invokestatic  #4                  // Method java/lang/Integer.valueOf:(I)Ljava/lang/Integer;
      31: invokevirtual #5                  // Method java/util/ArrayList.add:(Ljava/lang/Object;)Z
      34: pop
      35: aload_1
      36: invokevirtual #6                  // Method java/util/ArrayList.iterator:()Ljava/util/Iterator;
      39: astore_2
      40: aload_2
      41: invokeinterface #7,  1            // InterfaceMethod java/util/Iterator.hasNext:()Z
      46: ifeq          65
      49: aload_2
      50: invokeinterface #8,  1            // InterfaceMethod java/util/Iterator.next:()Ljava/lang/Object;
      55: astore_3
      56: aload_1
      57: aload_3
      58: invokevirtual #9                  // Method java/util/ArrayList.remove:(Ljava/lang/Object;)Z
      61: pop
      62: goto          40
      65: aload_1
      66: invokevirtual #6                  // Method java/util/ArrayList.iterator:()Ljava/util/Iterator;
      69: astore_2
      70: aload_2
      71: invokeinterface #7,  1            // InterfaceMethod java/util/Iterator.hasNext:()Z
      76: ifeq          95
      79: aload_2
      80: invokeinterface #8,  1            // InterfaceMethod java/util/Iterator.next:()Ljava/lang/Object;
      85: astore_3
      86: aload_2
      87: invokeinterface #10,  1           // InterfaceMethod java/util/Iterator.remove:()V
      92: goto          70
      95: getstatic     #11                 // Field java/lang/System.out:Ljava/io/PrintStream;
      98: aload_1
      99: invokevirtual #12                 // Method java/io/PrintStream.println:(Ljava/lang/Object;)V
     102: return
}
